miniworldmaker/__init__.py
miniworldmaker/app/__init__.py
miniworldmaker/app/app.py
miniworldmaker/appearances/__init__.py
miniworldmaker/appearances/appearance.py
miniworldmaker/appearances/appearances.py
miniworldmaker/appearances/background.py
miniworldmaker/appearances/costume.py
miniworldmaker/board_positions/__init__.py
miniworldmaker/board_positions/board_position.py
miniworldmaker/board_positions/board_rect.py
miniworldmaker/boards/__init__.py
miniworldmaker/boards/board.py
miniworldmaker/boards/physics_board.py
miniworldmaker/boards/pixel_board.py
miniworldmaker/boards/tiled_board.py
miniworldmaker/connectors/__init__.py
miniworldmaker/connectors/board_connector.py
miniworldmaker/connectors/physics_connector.py
miniworldmaker/connectors/pixel_connector.py
miniworldmaker/connectors/tiled_connector.py
miniworldmaker/containers/__init__.py
miniworldmaker/containers/actionbar.py
miniworldmaker/containers/color_toolbar.py
miniworldmaker/containers/console.py
miniworldmaker/containers/container.py
miniworldmaker/containers/event_console.py
miniworldmaker/containers/inspect_actor_toolbar.py
miniworldmaker/containers/level_designer_toolbar.py
miniworldmaker/containers/toolbar.py
miniworldmaker/containers/toolbar_widgets.py
miniworldmaker/physics/__init__.py
miniworldmaker/physics/physics.py
miniworldmaker/resources/down.png
miniworldmaker/resources/left.png
miniworldmaker/resources/logo_big.png
miniworldmaker/resources/logo_small.png
miniworldmaker/resources/logo_small_32.png
miniworldmaker/resources/pause.png
miniworldmaker/resources/play.png
miniworldmaker/resources/question.png
miniworldmaker/resources/reset.png
miniworldmaker/resources/right.png
miniworldmaker/resources/run.png
miniworldmaker/resources/up.png
miniworldmaker/tokens/__init__.py
miniworldmaker/tokens/actor.py
miniworldmaker/tokens/number_token.py
miniworldmaker/tokens/shapes.py
miniworldmaker/tokens/text_token.py
miniworldmaker/tokens/token.py
miniworldmaker/tools/__init__.py
miniworldmaker-1.5.0.dist-info/LICENSE.txt
miniworldmaker-1.5.0.dist-info/METADATA
miniworldmaker-1.5.0.dist-info/WHEEL
miniworldmaker-1.5.0.dist-info/top_level.txt
miniworldmaker-1.5.0.dist-info/RECORD
