Metadata-Version: 2.1
Name: miniworldmaker
Version: 1.5.0
Summary: Create 2D Miniworlds and Games
Home-page: https://github.com/asbl/miniworldmaker
Author: Andreas Siebel
Author-email: andreas.siebel@it-teaching.de
License: OSI Approved :: MIT License
Download-URL: https://github.com/asbl/miniworldmaker
Keywords: games,education,mini-worlds
Platform: UNKNOWN
Classifier: License :: OSI Approved :: MIT License
Classifier: Programming Language :: Python
Classifier: Development Status :: 4 - Beta
Classifier: Intended Audience :: Education
Classifier: Topic :: Education
Requires-Dist: pygame (>=2.0.1)
Requires-Dist: pymunk (<=5.6.0,>=5.6.0)
Requires-Dist: asyncio
Requires-Dist: nest-asyncio
Requires-Dist: deprecated
